docpie/__init__.py
docpie/bashlog.py
docpie/complete.py
docpie/element.py
docpie/error.py
docpie/parser.py
docpie/pie.py
docpie/test.py
docpie/tokens.py
docpie/tracemore.py
docpie/example/calculator_example.py
docpie/example/change_section_title_example.py
docpie/example/counted_example.py
docpie/example/cp.py
docpie/example/customize_output_and_exit_code.py
docpie/example/hide_options_in_help_extra.py
docpie/example/hide_options_in_help_inherit.py
docpie/example/interactive_example.py
docpie/example/naval_fate.py
docpie/example/odd_even_example.py
docpie/example/option_format_example.py
docpie/example/option_format_indent_example.py
docpie/example/options_shortcut_example.py
docpie/example/quick_example.py
docpie/example/serialization.py
docpie/example/git/__init__.py
docpie/example/git/git.py
docpie/example/git/git_add.py
docpie/example/git/git_branch.py
docpie/example/git/git_checkout.py
docpie/example/git/git_clone.py
docpie/example/git/git_commit.py
docpie/example/git/git_push.py
docpie/example/git/git_remote.py
docpie-0.4.4.dist-info/LICENSE
docpie-0.4.4.dist-info/METADATA
docpie-0.4.4.dist-info/WHEEL
docpie-0.4.4.dist-info/top_level.txt
docpie-0.4.4.dist-info/RECORD
