Metadata-Version: 2.1
Name: docpie
Version: 0.4.4
Summary: An easy and Pythonic way to create your POSIX command line interface
Home-page: http://docpie.comes.today/
Download-URL: https://github.com/TylerTemp/docpie/tarball/0.4.4/
Author: TylerTemp
Author-email: tylertempdev@gmail.com
License: MIT
Keywords: option arguments parsing optparse argparse getopt docopt
Platform: any
Classifier: Development Status :: 2 - Pre-Alpha
Classifier: License :: OSI Approved :: MIT License
Classifier: Topic :: Utilities
Classifier: Operating System :: OS Independent
Classifier: Programming Language :: Python :: 2
Classifier: Programming Language :: Python :: 2.6
Classifier: Programming Language :: Python :: 2.7
Classifier: Programming Language :: Python :: 3
Classifier: Programming Language :: Python :: 3.2
Classifier: Programming Language :: Python :: 3.3
Classifier: Programming Language :: Python :: 3.4
Classifier: Programming Language :: Python :: 3.5
Classifier: Programming Language :: Python :: Implementation :: PyPy
License-File: LICENSE
